{
  "Tool_water_bill_Title": "വാട്ടർ ബിൽ കാൽക്കുലേറ്റർ",
  "Tool_water_bill_Description": "കിലോലിറ്റർ സ്ലാബുകളും ഫിക്സഡ് ചാർജും ഉപയോഗിച്ച് വാട്ടർ ബിൽ കണക്കാക്കുക.",
  "Tool_water_bill_Subtitle": "kl × സ്ലാബ് നിരക്കുകൾ + ഫിക്സഡ്",
  "Tool_water_bill_LabelKl": "ഉപയോഗം (kl)",
  "Tool_water_bill_LabelFixed": "ഫിക്സഡ് / മീറ്റർ ചാർജ് (₹)",
  "Tool_water_bill_Result_Total": "മൊത്തം ബിൽ",
  "Tool_water_bill_Result_Usage": "ഉപയോഗ ചാർജ്",
  "Tool_water_bill_Result_Fixed": "ഫിക്സഡ് ചാർജ്",
  "Tool_savings_account_interest_Title": "സേവിംഗ്സ് അക്കൗണ്ട് പലിശ കാൽക്കുലേറ്റർ",
  "Tool_savings_account_interest_Description": "ബാലൻസ്, നിരക്ക് (~2.7–3%), ദിവസങ്ങൾ എന്നിവയിൽ നിന്ന് പലിശ — 80TTA കുറിപ്പോടെ.",
  "Tool_savings_account_interest_Subtitle": "ബാലൻസ് × നിരക്ക് × ദിവസങ്ങൾ / 365",
  "Tool_savings_account_interest_LabelBalance": "ശരാശരി ബാലൻസ് (₹)",
  "Tool_savings_account_interest_LabelRate": "പലിശ നിരക്ക് (% വാർഷികം)",
  "Tool_savings_account_interest_LabelDays": "ദിവസങ്ങളുടെ എണ്ണം",
  "Tool_savings_account_interest_Result_Interest": "കണക്കാക്കിയ പലിശ",
  "Tool_savings_account_interest_Result_Taxable": "80TTA-യ്ക്ക് മുകളിൽ",
  "Tool_sovereign_gold_bond_Title": "സോവറിൻ ഗോൾഡ് ബോണ്ട് കാൽക്കുലേറ്റർ",
  "Tool_sovereign_gold_bond_Description": "SGB റിട്ടേൺ: ഇഷ്യൂ വിലയിൽ 2.5% വാർഷിക പലിശ + റിഡംപ്ഷനിൽ മൂലധന നേട്ടം.",
  "Tool_sovereign_gold_bond_Subtitle": "2.5% പലിശ + മെച്യൂരിറ്റിയിൽ സ്വർണ്ണ വില",
  "Tool_sovereign_gold_bond_LabelGrams": "ഗ്രാം / യൂണിറ്റുകൾ",
  "Tool_sovereign_gold_bond_LabelIssue": "ഇഷ്യൂ വില (₹/ഗ്രാം)",
  "Tool_sovereign_gold_bond_LabelRedeem": "കണക്കാക്കിയ റിഡംപ്ഷൻ വില (₹/ഗ്രാം)",
  "Tool_sovereign_gold_bond_Result_Total": "മൊത്തം റിട്ടേൺ",
  "Tool_sovereign_gold_bond_Result_Interest": "മൊത്തം പലിശ",
  "Tool_sovereign_gold_bond_Result_Gain": "മൂലധന നേട്ടം",
  "Tool_senior_citizen_fd_Title": "സീനിയർ സിറ്റിസൺ FD കാൽക്കുലേറ്റർ",
  "Tool_senior_citizen_fd_Description": "ഉയർന്ന നിരക്കിൽ സീനിയർ FD മെച്യൂരിറ്റി, TDS കുറിപ്പ്, സാധാരണ FD-യുമായി താരതമ്യം.",
  "Tool_senior_citizen_fd_Subtitle": "ഉയർന്ന നിരക്ക് FD + സീനിയർ TDS കുറിപ്പ്",
  "Tool_senior_citizen_fd_LabelPrincipal": "നിക്ഷേപ തുക (₹)",
  "Tool_senior_citizen_fd_LabelRate": "സീനിയർ FD നിരക്ക് (% വാർഷികം)",
  "Tool_senior_citizen_fd_LabelYears": "കാലാവധി (വർഷങ്ങൾ)",
  "Tool_senior_citizen_fd_Result_Maturity": "നെറ്റ് മെച്യൂരിറ്റി",
  "Tool_senior_citizen_fd_Result_Interest": "നെറ്റ് പലിശ",
  "Tool_term_insurance_Title": "ടേം ഇൻഷുറൻസ് കാൽക്കുലേറ്റർ",
  "Tool_term_insurance_Description": "വരുമാനം×വർഷങ്ങൾ അല്ലെങ്കിൽ ചെലവ് രീതിയിൽ കവർ ആവശ്യം — നിലവിലുള്ള കവറുമായുള്ള വിടവ്.",
  "Tool_term_insurance_Subtitle": "വരുമാനം അല്ലെങ്കിൽ ചെലവ് രീതി → കവർ വിടവ്",
  "Tool_term_insurance_LabelMethod": "കവർ രീതി",
  "Tool_term_insurance_LabelIncome": "വാർഷിക വരുമാനം (₹)",
  "Tool_term_insurance_LabelLiabilities": "കുടിശ്ശിക കടങ്ങൾ (₹)",
  "Tool_term_insurance_LabelExisting": "നിലവിലുള്ള ലൈഫ് കവർ (₹)",
  "Tool_term_insurance_Result_Suggested": "നിർദ്ദേശിച്ച കവർ",
  "Tool_term_insurance_Result_Gap": "കവർ വിടവ്",
  "Tool_nri_tax_Title": "NRI ടാക്സ് കാൽക്കുലേറ്റർ",
  "Tool_nri_tax_Description": "താമസ സ്ഥിതി അനുസരിച്ച് ഇന്ത്യൻ വരുമാനത്തിലെ ഏകദേശ നികുതി — ലളിതമാക്കിയ സ്ലാബുകൾ.",
  "Tool_nri_tax_Subtitle": "താമസ സ്ഥിതി + ഇന്ത്യൻ വരുമാനം → ഏകദേശ നികുതി",
  "Tool_nri_tax_LabelStatus": "താമസ സ്ഥിതി",
  "Tool_nri_tax_LabelIncome": "ഇന്ത്യ-ഉറവിട വരുമാനം (₹)",
  "Tool_nri_tax_Result_Tax": "കണക്കാക്കിയ നികുതി",
  "Tool_nri_tax_Result_Income": "ഇന്ത്യൻ വരുമാനം",
  "Tool_nri_tax_Result_Effective": "ഫലപ്രദമായ നിരക്ക്"
}
